README.md
setup.py
sentry_asgi/__init__.py
sentry_asgi/middleware.py
sentry_asgi.egg-info/PKG-INFO
sentry_asgi.egg-info/SOURCES.txt
sentry_asgi.egg-info/dependency_links.txt
sentry_asgi.egg-info/requires.txt
sentry_asgi.egg-info/top_level.txt